leeway/__init__.py
leeway/__main__.py
leeway/cli.py
leeway-2023.10.22.dist-info/LICENSE
leeway-2023.10.22.dist-info/METADATA
leeway-2023.10.22.dist-info/WHEEL
leeway-2023.10.22.dist-info/entry_points.txt
leeway-2023.10.22.dist-info/top_level.txt
leeway-2023.10.22.dist-info/RECORD
